syntactic/__init__.py
uzbeksyntactic/__init__.py
uzbeksyntactic-0.3.dist-info/LICENSE.txt
uzbeksyntactic-0.3.dist-info/METADATA
uzbeksyntactic-0.3.dist-info/WHEEL
uzbeksyntactic-0.3.dist-info/top_level.txt
uzbeksyntactic-0.3.dist-info/RECORD
