Metadata-Version: 2.1
Name: uzbeksyntactic
Version: 0.3
Summary: This package is desgined to help researcher to develop syntactic algorithm for uzbek language
Home-page: UNKNOWN
Author: Ismailov Alisher Shakirovich, Nilufar Abdurahmonova
Author-email: alisherismailov1991@gmail.com
License: MIT
Platform: UNKNOWN
Classifier: Programming Language :: Python :: 3
Classifier: License :: OSI Approved :: MIT License
Classifier: Operating System :: OS Independent
License-File: LICENSE.txt
